tabgenie/__init__.py
tabgenie/cli.py
tabgenie/config.yml
tabgenie/main.py
tabgenie/loaders/__init__.py
tabgenie/loaders/cacapo.py
tabgenie/loaders/charttotext_s.py
tabgenie/loaders/dart.py
tabgenie/loaders/e2e.py
tabgenie/loaders/eventnarrative.py
tabgenie/loaders/hitab.py
tabgenie/loaders/logic2text.py
tabgenie/loaders/logicnlg.py
tabgenie/loaders/multiwoz22.py
tabgenie/loaders/numericnlg.py
tabgenie/loaders/scigen.py
tabgenie/loaders/sportsett.py
tabgenie/loaders/totto.py
tabgenie/loaders/webnlg.py
tabgenie/loaders/wikibio.py
tabgenie/loaders/wikisql.py
tabgenie/loaders/wikitabletext.py
tabgenie/processing/__init__.py
tabgenie/processing/processing.py
tabgenie/processing/pipelines/__init__.py
tabgenie/processing/pipelines/export_pipeline.py
tabgenie/processing/pipelines/graph_pipeline.py
tabgenie/processing/pipelines/model_api_pipeline.py
tabgenie/processing/pipelines/model_local_pipeline.py
tabgenie/processing/pipelines/text_ie_pipeline.py
tabgenie/processing/pipelines/translate_pipeline.py
tabgenie/processing/processors/__init__.py
tabgenie/processing/processors/custom_input_processor.py
tabgenie/processing/processors/export_processor.py
tabgenie/processing/processors/graph_processor.py
tabgenie/processing/processors/linearize_processor.py
tabgenie/processing/processors/model_api_processor.py
tabgenie/processing/processors/model_local_processor.py
tabgenie/processing/processors/reference_processor.py
tabgenie/processing/processors/table_triple_processor.py
tabgenie/processing/processors/text_ie_processor.py
tabgenie/processing/processors/translate_processor.py
tabgenie/static/css/bootstrap-grid.min.css
tabgenie/static/css/bootstrap-grid.rtl.min.css
tabgenie/static/css/bootstrap-reboot.min.css
tabgenie/static/css/bootstrap-utilities.min.css
tabgenie/static/css/bootstrap.min.css
tabgenie/static/css/bootstrap.rtl.min.css
tabgenie/static/css/custom.css
tabgenie/static/css/d3graphs.css
tabgenie/static/css/jquery.highlight-within-textarea.css
tabgenie-0.0.1.dist-info/LICENSE
tabgenie-0.0.1.dist-info/METADATA
tabgenie-0.0.1.dist-info/WHEEL
tabgenie-0.0.1.dist-info/entry_points.txt
tabgenie-0.0.1.dist-info/top_level.txt
tabgenie-0.0.1.dist-info/RECORD
