Metadata-Version: 2.1
Name: tabgenie
Version: 0.0.1
Summary: TabGenie: A toolkit for table-to-text generation.
Home-page: https://github.com/kasnerz/tabgenie
Author: Zdenek Kasner, Ekaterina Garanina, Ondrej Dusek
Author-email: kasner@ufal.mff.cuni.cz
License: Apache-2.0 License
Classifier: Development Status :: 3 - Alpha
Classifier: Programming Language :: Python :: 3.8
Classifier: Programming Language :: Python :: 3.9
Classifier: Programming Language :: Python :: 3.10
Classifier: Intended Audience :: Science/Research
Classifier: Operating System :: POSIX :: Linux
Classifier: License :: OSI Approved :: Apache Software License
Classifier: Topic :: Scientific/Engineering :: Artificial Intelligence
Classifier: Topic :: Software Development :: Libraries :: Python Modules
Classifier: Typing :: Typed
Requires-Python: >=3.8
License-File: LICENSE
Requires-Dist: Flask (>=2.2.2)
Requires-Dist: datasets (>=2.9.0)
Requires-Dist: requests
Requires-Dist: lxml
Requires-Dist: tinyhtml
Requires-Dist: xlsxwriter
Requires-Dist: coloredlogs
Provides-Extra: deploy
Requires-Dist: gunicorn ; extra == 'deploy'
Provides-Extra: dev
Requires-Dist: wheel ; extra == 'dev'
Requires-Dist: black ; extra == 'dev'
